<annotation>
	<filename>2009_002952.jpg</filename>
	<folder>VOC2012</folder>
	<object>
		<name>pottedplant</name>
		<bndbox>
			<xmax>363</xmax>
			<xmin>330</xmin>
			<ymax>207</ymax>
			<ymin>96</ymin>
		</bndbox>
		<difficult>0</difficult>
		<occluded>0</occluded>
		<pose>Unspecified</pose>
		<truncated>0</truncated>
	</object>
	<object>
		<name>pottedplant</name>
		<bndbox>
			<xmax>477</xmax>
			<xmin>453</xmin>
			<ymax>235</ymax>
			<ymin>170</ymin>
		</bndbox>
		<difficult>0</difficult>
		<occluded>0</occluded>
		<pose>Unspecified</pose>
		<truncated>0</truncated>
	</object>
	<object>
		<name>pottedplant</name>
		<bndbox>
			<xmax>461</xmax>
			<xmin>434</xmin>
			<ymax>229</ymax>
			<ymin>132</ymin>
		</bndbox>
		<difficult>0</difficult>
		<occluded>0</occluded>
		<pose>Unspecified</pose>
		<truncated>0</truncated>
	</object>
	<object>
		<name>pottedplant</name>
		<bndbox>
			<xmax>395</xmax>
			<xmin>346</xmin>
			<ymax>236</ymax>
			<ymin>171</ymin>
		</bndbox>
		<difficult>0</difficult>
		<occluded>0</occluded>
		<pose>Unspecified</pose>
		<truncated>0</truncated>
	</object>
	<object>
		<name>pottedplant</name>
		<bndbox>
			<xmax>411</xmax>
			<xmin>395</xmin>
			<ymax>221</ymax>
			<ymin>163</ymin>
		</bndbox>
		<difficult>0</difficult>
		<occluded>0</occluded>
		<pose>Unspecified</pose>
		<truncated>0</truncated>
	</object>
	<object>
		<name>pottedplant</name>
		<bndbox>
			<xmax>434</xmax>
			<xmin>411</xmin>
			<ymax>225</ymax>
			<ymin>187</ymin>
		</bndbox>
		<difficult>0</difficult>
		<occluded>0</occluded>
		<pose>Unspecified</pose>
		<truncated>0</truncated>
	</object>
</annotation>
